setup.py
eligible/__init__.py
eligible/errors.py
eligible/header.py
eligible/resources.py
eligible/url.py
eligible.egg-info/PKG-INFO
eligible.egg-info/SOURCES.txt
eligible.egg-info/dependency_links.txt
eligible.egg-info/not-zip-safe
eligible.egg-info/requires.txt
eligible.egg-info/top_level.txt