Metadata-Version: 1.0
Name: eligible
Version: 1.1.4
Summary: Python bindings for the Eligible API
Home-page: http://github.com/EligibleAPI/eligible-python
Author: Sourceless
Author-email: laurence@eligibleapi.com
License: MIT
Keywords: eligible api healthcare rest
Platform: UNKNOWN
